apache_libcloud-0.18.0.dist-info/pbr.json
apache_libcloud-0.18.0.dist-info/RECORD
apache_libcloud-0.18.0.dist-info/metadata.json
apache_libcloud-0.18.0.dist-info/top_level.txt
apache_libcloud-0.18.0.dist-info/METADATA
apache_libcloud-0.18.0.dist-info/WHEEL
apache_libcloud-0.18.0.dist-info/DESCRIPTION.rst
libcloud/httplib_ssl.py
libcloud/__init__.py
libcloud/security.py
libcloud/pricing.py
libcloud/utils/files.py
libcloud/utils/logging.py
libcloud/utils/decorators.py
libcloud/utils/dist.py
libcloud/utils/py3.py
libcloud/utils/iso8601.py
libcloud/utils/__init__.py
libcloud/utils/connection.py
libcloud/utils/networking.py
libcloud/utils/compression.py
libcloud/utils/xml.py
libcloud/utils/publickey.py
libcloud/utils/misc.py
libcloud/compute/__init__.py
libcloud/compute/providers.py
libcloud/compute/deployment.py
libcloud/compute/ssh.py
libcloud/compute/base.py
libcloud/compute/types.py
libcloud/compute/drivers/hpcloud.py
libcloud/compute/drivers/openstack.py
libcloud/compute/drivers/ktucloud.py
libcloud/compute/drivers/runabove.py
libcloud/compute/drivers/cloudstack.py
libcloud/compute/drivers/vcl.py
libcloud/compute/drivers/vultr.py
libcloud/compute/drivers/ec2.py
libcloud/compute/drivers/ikoula.py
libcloud/compute/drivers/auroracompute.py
libcloud/compute/drivers/azure.py
libcloud/compute/drivers/gridspot.py
libcloud/compute/drivers/vsphere.py
libcloud/compute/drivers/libvirt_driver.py
libcloud/compute/drivers/hostvirtual.py
libcloud/compute/drivers/vcloud.py
libcloud/compute/drivers/dimensiondata.py
libcloud/compute/drivers/dummy.py
libcloud/compute/drivers/elastichosts.py
libcloud/compute/drivers/voxel.py
libcloud/compute/drivers/ibm_sce.py
libcloud/compute/drivers/elasticstack.py
libcloud/compute/drivers/cloudframes.py
libcloud/compute/drivers/rackspace.py
libcloud/compute/drivers/gogrid.py
libcloud/compute/drivers/__init__.py
libcloud/compute/drivers/kili.py
libcloud/compute/drivers/digitalocean.py
libcloud/compute/drivers/gandi.py
libcloud/compute/drivers/joyent.py
libcloud/compute/drivers/abiquo.py
libcloud/compute/drivers/vpsnet.py
libcloud/compute/drivers/ninefold.py
libcloud/compute/drivers/rimuhosting.py
libcloud/compute/drivers/opennebula.py
libcloud/compute/drivers/softlayer.py
